Metadata-Version: 2.4
Name: terra-classic-data-analysis-sdk
Version: 0.2.5
Summary: The Python SDK for Terra Classic Data Analysis
License: MIT
License-File: LICENSE
Keywords: terra,terra classic,lunc,lunc sdk,terra.py,terra sdk,luna classic,luna classic sdk,lunc sdk,lunc analysis,terra analysis,terra classic analysis,lunc data,terra data,terra classic data
Author: Binodes
Author-email: postmaster@binodes.com
Requires-Python: >=3.10,<4.0
Classifier: Intended Audience :: Developers
Classifier: License :: OSI Approved :: MIT License
Classifier: Natural Language :: English
Classifier: Programming Language :: Python :: 3
Classifier: Programming Language :: Python :: 3.10
Classifier: Programming Language :: Python :: 3.11
Classifier: Programming Language :: Python :: 3.12
Classifier: Programming Language :: Python :: 3.13
Classifier: Programming Language :: Python :: 3.14
Classifier: Programming Language :: Python :: 3.7
Classifier: Programming Language :: Python :: 3.8
Classifier: Programming Language :: Python :: 3.9
Requires-Dist: aiohttp (>=3.9.1,<4.0.0)
Requires-Dist: attrs (>=23.1.0,<24.0.0)
Requires-Dist: bech32 (>=1.2.0,<2.0.0)
Requires-Dist: betterproto (==2.0.0b4)
Requires-Dist: bip32utils (>=0.3.post4,<0.4)
Requires-Dist: boltons (>=23.1.1,<24.0.0)
Requires-Dist: ecdsa (>=0.18.0,<0.19.0)
Requires-Dist: furl (>=2.1.3,<3.0.0)
Requires-Dist: mnemonic (>=0.20,<0.21)
Requires-Dist: nest-asyncio (>=1.5.8,<2.0.0)
Requires-Dist: protobuf (>=4.25.1,<5.0.0)
Requires-Dist: terra-classic-proto (>=4.0.0,<5.0.0)
Requires-Dist: wrapt (>=1.16.0,<2.0.0)
Project-URL: Documentation, https://terra-money.github.io/terra.py/index.html
Project-URL: Homepage, https://github.com/BInodes-official/terra.py
Project-URL: Repository, https://github.com/BInodes-official/terra.py
